KhtabXS
