Metadata-Version: 2.4
Name: KhtabXS
Version: 1.2
Summary: تم صنع بواسطة فريق XS ~ الصانع الرسمي ^[خطاب]^ ~ مساعده ^[سجاد]^
Author: KhtabXS
Classifier: Programming Language :: Python :: 3.11
Requires-Python: >=3.0
